{
  "info": [
    {
      "index": "/article-2024/07/make-scratch-comment-emulator/",
      "thumbnail": "/article-2024/07/make-scratch-comment-emulator/thumbnail.jpeg",
      "name": "make-scratch-comment-emulator",
      "title": "Scratch Comment emulator\u3092\u4f5c\u3063\u3066\u307f\u305f\uff01",
      "date": "2024/07/02"
    },
    {
      "index": "/article-2024/07/make-Infinity-ads/",
      "thumbnail": "/article-2024/07/make-Infinity-ads/thumbnail.svg",
      "name": "make-Infinity-ads",
      "title": "\u30d6\u30ed\u30b0\u306b\u5e83\u544a\u3092\u8f09\u305b\u305f\u3044",
      "date": "2024/07/02"
    }
  ]
}