{
  "info": [
    {
      "name":"SEO-1",
      "thumbnail":"/blog-data/data/SEO_1/thumbnail.png",
      "title":"SEO対策やってみた その一",
      "html":"/BLOG/data/SEO_1/index.html"
    },
    {
      "name": "I think about Scratch",
      "thumbnail": "/blog-data/data/i_think_about_scratch/thumbnail.png",
      "title": "Scratchについて思うこと",
      "html": "/BLOG/data/i_think_about_scratch/index.html"
    },
    {
      "name": "First test",
      "thumbnail": "/blog-data/data/test/thumbnail.png",
      "title": "First test!",
      "html": "/BLOG/data/test/index.html"
    }
  ]
}
